deci_common/__init__.py
deci_common/abstractions/__init__.py
deci_common/abstractions/abstract_logger.py
deci_common/abstractions/base_model.py
deci_common/auto_logging/__init__.py
deci_common/auto_logging/auto_logger.py
deci_common/auto_logging/auto_logging_conf.json
deci_common/aws_connection/__init__.py
deci_common/aws_connection/aws_connector.py
deci_common/data_connection/__init__.py
deci_common/data_connection/mongo_connector.py
deci_common/data_connection/s3_connector.py
deci_common/data_interfaces/__init__.py
deci_common/data_interfaces/files_data_interface.py
deci_common/data_interfaces/generic_db_interface.py
deci_common/data_interfaces/mongo_db_interface.py
deci_common/data_types/__init__.py
deci_common/data_types/enum/__init__.py
deci_common/data_types/enum/dataset_names.py
deci_common/data_types/enum/deep_learning_task.py
deci_common/data_types/enum/hardware_enums.py
deci_common/data_types/enum/inference_transport.py
deci_common/data_types/enum/model_frameworks.py
deci_common/data_types/enum/models_enums.py
deci_common/data_types/enum/open_vino_checkpoint_types.py
deci_common/data_types/hardware.py
deci_common/data_types/inferencer_data_types.py
deci_common/data_types/model_errors.py
deci_common/environment/__init__.py
deci_common/environment/environment_config.py
deci_common/helpers.py
deci_common/py.typed
deci_common-13.1.1.dist-info/LICENSE.md
deci_common-13.1.1.dist-info/METADATA
deci_common-13.1.1.dist-info/WHEEL
deci_common-13.1.1.dist-info/RECORD
